goodmem_client/__init__.py
goodmem_client/api_client.py
goodmem_client/api_response.py
goodmem_client/configuration.py
goodmem_client/exceptions.py
goodmem_client/py.typed
goodmem_client/rest.py
goodmem_client/streaming.py
goodmem_client/api/__init__.py
goodmem_client/api/administration_api.py
goodmem_client/api/api_keys_api.py
goodmem_client/api/embedders_api.py
goodmem_client/api/llms_api.py
goodmem_client/api/memories_api.py
goodmem_client/api/rerankers_api.py
goodmem_client/api/spaces_api.py
goodmem_client/api/system_api.py
goodmem_client/api/users_api.py
goodmem_client/models/__init__.py
goodmem_client/models/abstract_reply.py
goodmem_client/models/active_license_metadata.py
goodmem_client/models/admin_drain_request.py
goodmem_client/models/admin_drain_response.py
goodmem_client/models/admin_purge_jobs_request.py
goodmem_client/models/admin_purge_jobs_response.py
goodmem_client/models/admin_reload_license_response.py
goodmem_client/models/api_key_auth.py
goodmem_client/models/api_key_response.py
goodmem_client/models/background_job_attempt.py
goodmem_client/models/background_job_summary.py
goodmem_client/models/batch_memory_creation_request.py
goodmem_client/models/batch_memory_deletion_request.py
goodmem_client/models/batch_memory_response.py
goodmem_client/models/batch_memory_result.py
goodmem_client/models/batch_memory_retrieval_request.py
goodmem_client/models/binary_content.py
goodmem_client/models/chunk_reference.py
goodmem_client/models/chunking_configuration.py
goodmem_client/models/context_item.py
goodmem_client/models/create_api_key_request.py
goodmem_client/models/create_api_key_response.py
goodmem_client/models/create_llm_response.py
goodmem_client/models/credential_kind.py
goodmem_client/models/distribution_type.py
goodmem_client/models/embedder_creation_request.py
goodmem_client/models/embedder_response.py
goodmem_client/models/embedder_weight.py
goodmem_client/models/endpoint_authentication.py
goodmem_client/models/error_detail.py
goodmem_client-1.5.9.dist-info/METADATA
goodmem_client-1.5.9.dist-info/WHEEL
goodmem_client-1.5.9.dist-info/top_level.txt
goodmem_client-1.5.9.dist-info/RECORD
