Metadata-Version: 2.4
Name: goodmem-client
Version: 1.5.9
Summary: API for interacting with the GoodMem service, providing vector-based memory storage and retrieval with multiple embedder support.
Home-page: https://github.com/PAIR-Systems-Inc/goodmem
Author: GoodMem API Support
Author-email: support@goodmem.io
License: Apache 2.0
Project-URL: Bug Reports, https://github.com/PAIR-Systems-Inc/goodmem/issues
Project-URL: Source, https://github.com/PAIR-Systems-Inc/goodmem/tree/main/clients/python
Project-URL: PyPI, https://pypi.org/project/goodmem-client/
Keywords: OpenAPI,OpenAPI-Generator,GoodMem API,vector,embeddings,memory
Classifier: Development Status :: 4 - Beta
Classifier: Intended Audience :: Developers
Classifier: License :: OSI Approved :: Apache Software License
Classifier: Programming Language :: Python :: 3
Classifier: Programming Language :: Python :: 3.9
Classifier: Programming Language :: Python :: 3.10
Classifier: Programming Language :: Python :: 3.11
Classifier: Programming Language :: Python :: 3.12
Classifier: Programming Language :: Python :: 3.13
Classifier: Topic :: Software Development :: Libraries :: Python Modules
Classifier: Topic :: Internet :: WWW/HTTP
Classifier: Topic :: Scientific/Engineering :: Artificial Intelligence
Requires-Python: >= 3.9
Requires-Dist: urllib3>=2.1.0
Requires-Dist: python-dateutil>=2.8.2
Requires-Dist: pydantic>=2
Requires-Dist: typing-extensions>=4.7.1
Dynamic: author
Dynamic: author-email
Dynamic: classifier
Dynamic: description
Dynamic: description-content-type
Dynamic: home-page
Dynamic: keywords
Dynamic: license
Dynamic: project-url
Dynamic: requires-dist
Dynamic: requires-python
Dynamic: summary
